MANIFEST.in
setup.py
alice_pi/__init__.py
alice_pi/configurers.py
alice_pi/managers.py
alice_pi/measurers.py
alice_pi/senders.py
alice_pi.egg-info/PKG-INFO
alice_pi.egg-info/SOURCES.txt
alice_pi.egg-info/dependency_links.txt
alice_pi.egg-info/entry_points.txt
alice_pi.egg-info/requires.txt
alice_pi.egg-info/top_level.txt
alice_pi/bin/__init__.py
alice_pi/bin/run_alice.py
alice_pi/data/alice_pi.service.example
alice_pi/data/alice_pi_config.yml.example
alice_pi/tests/__init__.py
alice_pi/tests/test_configurers.py
alice_pi/tests/test_managers.py
alice_pi/tests/test_measurers.py
alice_pi/tests/test_senders.py