Metadata-Version: 1.1
Name: alice-pi
Version: 0.0.12
Summary: A package for running various home-automationservices on raspberry pi.
Home-page: https://github.com/jlmcgehee21/alice_pi
Author: Jeff Mcgehee
Author-email: jlmcgehee21@gmail.com
License: MIT
Keywords: automation sensors raspberrypi
Platform: UNKNOWN
Classifier: Development Status :: 3 - Alpha
Classifier: Intended Audience :: Developers
Classifier: License :: OSI Approved :: MIT License
Classifier: Programming Language :: Python :: 3.5
